MANIFEST.in
README.md
setup.py
Flask_NewProject/CreateDirs.py
Flask_NewProject/__init__.py
Flask_NewProject/blueprint.py
Flask_NewProject/script_info.py
Flask_NewProject/simple.py
Flask_NewProject/skeleton.py
Flask_NewProject.egg-info/PKG-INFO
Flask_NewProject.egg-info/SOURCES.txt
Flask_NewProject.egg-info/dependency_links.txt
Flask_NewProject.egg-info/entry_points.txt
Flask_NewProject.egg-info/not-zip-safe
Flask_NewProject.egg-info/top_level.txt
test/tests.py