Metadata-Version: 1.1
Name: Flask-NewProject
Version: 0.2.1
Summary: Create new Flask project.
Home-page: https://github.com/Gunak/Flask-NewProject/
Author: Raymond Williams
Author-email: Raymond.n.williams86@gmail.com
License: MIT
Platform: UNKNOWN
Classifier: Development Status :: 1 - Planning
Classifier: Framework :: Flask
Classifier: Intended Audience :: Developers
Classifier: License :: OSI Approved :: MIT License
Classifier: Natural Language :: English
Classifier: Programming Language :: Python :: 2.7
Classifier: Topic :: Utilities
